aat_analysis/__init__.py
aat_analysis/_nbdev.py
aat_analysis/add_responses.py
aat_analysis/constants.py
aat_analysis/core.py
aat_analysis/json_to_df.py
aat_analysis/make_condition_templates.py
aat_analysis/utils.py
aat_analysis-0.0.7.dist-info/LICENSE
aat_analysis-0.0.7.dist-info/METADATA
aat_analysis-0.0.7.dist-info/WHEEL
aat_analysis-0.0.7.dist-info/entry_points.txt
aat_analysis-0.0.7.dist-info/top_level.txt
aat_analysis-0.0.7.dist-info/RECORD
