Metadata-Version: 2.1
Name: aat-analysis
Version: 0.0.7
Summary: This project analyzes mobile AAT data.
Home-page: https://github.com/hgzech/aat_analysis/tree/master/
Author: Hilmar Zech
Author-email: hgzech@gmail.com
License: Apache Software License 2.0
Keywords: approach-avoidance-task AAT approach avoidance mobile maat
Platform: UNKNOWN
Classifier: Development Status :: 3 - Alpha
Classifier: Intended Audience :: Developers
Classifier: Natural Language :: English
Classifier: Programming Language :: Python :: 3.6
Classifier: Programming Language :: Python :: 3.7
Classifier: Programming Language :: Python :: 3.8
Classifier: License :: OSI Approved :: Apache Software License
Requires-Python: >=3.6
License-File: LICENSE
Requires-Dist: pip
Requires-Dist: packaging
Requires-Dist: scipy
Requires-Dist: pandas
Requires-Dist: tqdm
Requires-Dist: peakutils
Requires-Dist: matplotlib
Provides-Extra: dev
